mdln/__about__.py
mdln/__init__.py
mdln/const.py
mdln/game.py
mdln/icon.py
mdln/resource.py
mdln-0.1.4.dist-info/LICENSE
mdln-0.1.4.dist-info/METADATA
mdln-0.1.4.dist-info/WHEEL
mdln-0.1.4.dist-info/top_level.txt
mdln-0.1.4.dist-info/RECORD
