Metadata-Version: 2.1
Name: mdln
Version: 0.1.4
Summary: A lightweight, high performance, and object-focused 2D game framework in Python
Home-page: https://github.com/qwertyquerty/MDLN
Author: Madeline
License: MIT
Project-URL: Documentation, https://github.com/qwertyquerty/MDLN
Keywords: mdln game engine pygame entity component framework
Requires-Python: >=3.6
License-File: LICENSE
Requires-Dist: pygame (<3,>=2.2.0)
Requires-Dist: pyyaml (==6.0)
